IMAPClientLibrary/__init__.py
robotframework_IMAPClientLibrary-0.1.3.dist-info/METADATA
robotframework_IMAPClientLibrary-0.1.3.dist-info/WHEEL
robotframework_IMAPClientLibrary-0.1.3.dist-info/top_level.txt
robotframework_IMAPClientLibrary-0.1.3.dist-info/RECORD
