Metadata-Version: 2.1
Name: robotframework-IMAPClientLibrary
Version: 0.1.3
Summary: IMAPClientLibrary is a Test email library for Robot Framework.
Home-page: https://github.com/qahive/robotframework-imapclientlibrary
Author: QA Hive Co.,Ltd
Author-email: support@qahive.com
License: Apache License 2.0
Keywords: robotframework imapclient email-testing automation
Platform: any
Classifier: Programming Language :: Python :: 3
Classifier: Programming Language :: Python :: 3.6
Classifier: Programming Language :: Python :: 3.7
Classifier: License :: OSI Approved :: Apache Software License
Classifier: Operating System :: OS Independent
Classifier: Topic :: Software Development :: Testing
Classifier: Topic :: Software Development :: Testing :: Acceptance
Classifier: Framework :: Robot Framework
Requires-Dist: robotframework (>=3.2.1)
Requires-Dist: IMAPClient (>=2.1.0)
